microweldr/__init__.py
microweldr/__main__.py
microweldr/cli/__init__.py
microweldr/cli/config_setup.py
microweldr/cli/enhanced_main.py
microweldr/cli/main.py
microweldr/cli/monitor_print.py
microweldr/cli/printer_control.py
microweldr/cli/printer_status.py
microweldr/cli/simple_main.py
microweldr/cli/stop_print.py
microweldr/cli/temperature_control.py
microweldr/cli/workflow.py
microweldr/core/__init__.py
microweldr/core/app_constants.py
microweldr/core/bounding_box_subscriber.py
microweldr/core/caching.py
microweldr/core/config.py
microweldr/core/constants.py
microweldr/core/coordinate_centering.py
microweldr/core/data_models.py
microweldr/core/enhanced_converter.py
microweldr/core/enhanced_writers.py
microweldr/core/error_handling.py
microweldr/core/events.py
microweldr/core/file_factory.py
microweldr/core/frame_extent_calculator.py
microweldr/core/generator_factory.py
microweldr/core/graceful_degradation.py
microweldr/core/health_checks.py
microweldr/core/logging_config.py
microweldr/core/models.py
microweldr/core/printer_operations.py
microweldr/core/printer_service.py
microweldr/core/progress.py
microweldr/core/resource_management.py
microweldr/core/safety.py
microweldr/core/secrets_config.py
microweldr/core/unified_config.py
microweldr/generators/__init__.py
microweldr/generators/dxf_point_iterator.py
microweldr/generators/models.py
microweldr/generators/multipass_point_iterator.py
microweldr/generators/point_iterator.py
microweldr/generators/point_iterator_factory.py
microweldr/generators/svg_point_iterator.py
microweldr/outputs/__init__.py
microweldr/outputs/gif_animation_subscriber.py
microweldr/outputs/streaming_gcode_subscriber.py
microweldr/parsers/__init__.py
microweldr/parsers/dxf_reader.py
microweldr/parsers/enhanced_readers.py
microweldr/parsers/enhanced_svg_parser.py
microweldr/parsers/file_readers.py
microweldr/parsers/svg_parser.py
microweldr/parsers/svg_reader.py
microweldr/processors/__init__.py
microweldr/processors/event_processor.py
microweldr-6.1.4.dist-info/METADATA
microweldr-6.1.4.dist-info/WHEEL
microweldr-6.1.4.dist-info/entry_points.txt
microweldr-6.1.4.dist-info/licenses/LICENSE
microweldr-6.1.4.dist-info/RECORD
