Metadata-Version: 2.4
Name: microweldr
Version: 6.1.4
Summary: Convert SVG and DXF files to Prusa Core One G-code for plastic welding
License-Expression: MIT
License-File: LICENSE
Keywords: 3d-printing,welding,gcode,svg,dxf,prusa
Author: Reto Stamm
Author-email: reto@retostamm.com
Requires-Python: >=3.10
Classifier: Development Status :: 4 - Beta
Classifier: Intended Audience :: Developers
Classifier: Intended Audience :: Manufacturing
Classifier: Operating System :: OS Independent
Classifier: Programming Language :: Python :: 3
Classifier: Programming Language :: Python :: 3.10
Classifier: Programming Language :: Python :: 3.11
Classifier: Programming Language :: Python :: 3.12
Classifier: Programming Language :: Python :: 3.13
Classifier: Topic :: Multimedia :: Graphics :: Graphics Conversion
Classifier: Topic :: Scientific/Engineering :: Visualization
Requires-Dist: Pillow (>=10.0.0)
Requires-Dist: ezdxf (>=1.4.0)
Requires-Dist: lxml (>=5.0.0)
Requires-Dist: requests (>=2.25.0)
Requires-Dist: toml (>=0.10.2)
Project-URL: Documentation, https://github.com/retospect/microweldr
Project-URL: Homepage, https://github.com/retospect/microweldr
Project-URL: Repository, https://github.com/retospect/microweldr
